python_cayennelpp/__init__.py
python_cayennelpp/decoder.py
python_cayennelpp/methods.py
python_cayennelpp-0.1.0.dist-info/licenses/LICENSE
python_cayennelpp-0.1.0.dist-info/METADATA
python_cayennelpp-0.1.0.dist-info/WHEEL
python_cayennelpp-0.1.0.dist-info/top_level.txt
python_cayennelpp-0.1.0.dist-info/RECORD
