Metadata-Version: 2.4
Name: python-cayennelpp
Version: 0.1.0
Summary: A package to decode data encoded in the CayenneLPP format.
Author-email: Oleg Zvonarov <info+github@zvonarov.com>
Project-URL: Homepage, https://github.com/OlegZv/Python-CayenneLPP
Project-URL: Repository, https://github.com/OlegZv/Python-CayenneLPP
Project-URL: Issues, https://github.com/OlegZv/Python-CayenneLPP/issues
Classifier: Operating System :: OS Independent
Classifier: Topic :: Software Development :: Libraries :: Python Modules
Classifier: Programming Language :: Python :: 3
Classifier: Programming Language :: Python :: 2
Classifier: Programming Language :: Python :: 2.7
Classifier: Programming Language :: Python :: 3.4
Classifier: Programming Language :: Python :: 3.5
Classifier: Programming Language :: Python :: 3.6
Classifier: Programming Language :: Python :: 3.7
Classifier: Programming Language :: Python :: 3.8
Classifier: Programming Language :: Python :: 3.9
Classifier: Programming Language :: Python :: 3.10
Classifier: Programming Language :: Python :: 3.11
Classifier: Programming Language :: Python :: 3.12
Classifier: Programming Language :: Python :: 3.13
Requires-Python: >=3.8
License-File: LICENSE
Dynamic: license-file
